discordSuperUtils_nextcord
