Metadata-Version: 2.1
Name: discordSuperUtils-nextcord
Version: 0.3.2
Summary: Discord Bot Development made easy!
Home-page: https://github.com/I-dan-mi-I/nextcord-super-utils
Author: koyashie07 and adam7100. converted by i-dan-mi-i
License: MIT
Download-URL: https://github.com/I-dan-mi-I/nextcord-super-utils/releases/download/0.3.1/discordSuperUtils_nextcord-0.3.1.tar.gz
Keywords: nextcord,easy,music,download,links,images,videos,audio,bot,paginator,economy,reaction,reaction roles,database,database manager
Platform: UNKNOWN
Classifier: Development Status :: 4 - Beta
Classifier: Intended Audience :: Developers
Classifier: Topic :: Software Development :: Build Tools
Classifier: License :: OSI Approved :: MIT License
Classifier: Programming Language :: Python :: 3
Classifier: Programming Language :: Python :: 3.8
Classifier: Programming Language :: Python :: 3.9
Classifier: Programming Language :: Python :: 3.10
License-File: LICENSE
